actk/__init__.py
actk/constants.py
actk/exceptions.py
actk/bin/__init__.py
actk/bin/all.py
actk/bin/cli.py
actk/steps/__init__.py
actk/steps/diagnostic_sheets/__init__.py
actk/steps/diagnostic_sheets/diagnostic_sheets.py
actk/steps/raw/__init__.py
actk/steps/raw/raw.py
actk/steps/single_cell_features/__init__.py
actk/steps/single_cell_features/single_cell_features.py
actk/steps/single_cell_images/__init__.py
actk/steps/single_cell_images/single_cell_images.py
actk/steps/standardize_fov_array/__init__.py
actk/steps/standardize_fov_array/standardize_fov_array.py
actk/utils/__init__.py
actk/utils/dataset_utils.py
actk/utils/image_utils.py
actk-0.2.2.dist-info/LICENSE
actk-0.2.2.dist-info/METADATA
actk-0.2.2.dist-info/WHEEL
actk-0.2.2.dist-info/entry_points.txt
actk-0.2.2.dist-info/top_level.txt
actk-0.2.2.dist-info/RECORD
