Metadata-Version: 2.1
Name: actk
Version: 0.2.2
Summary: Automated Cell Toolkit
Home-page: https://github.com/AllenCellModeling/actk
Author: Jackson Maxfield Brown
Author-email: jacksonb@alleninstitute.org
License: Allen Institute Software License
Keywords: actk,computational biology,workflow,cell,microscopy
Platform: UNKNOWN
Classifier: Development Status :: 2 - Pre-Alpha
Classifier: Intended Audience :: Developers
Classifier: License :: Free for non-commercial use
Classifier: Natural Language :: English
Classifier: Programming Language :: Python :: 3.6
Classifier: Programming Language :: Python :: 3.7
Classifier: Programming Language :: Python :: 3.8
Requires-Python: >=3.6
Requires-Dist: aics-dask-utils (>=0.2.0)
Requires-Dist: bokeh (>=2.1.0)
Requires-Dist: dask[bag] (>=2.19.0)
Requires-Dist: dask-jobqueue (>=0.7.0)
Requires-Dist: datastep (>=0.1.8)
Requires-Dist: distributed (>=2.19.0)
Requires-Dist: fire
Requires-Dist: psutil
Requires-Dist: aicsfeature (>=0.2.1)
Requires-Dist: aicsimageio (>=3.2.3)
Requires-Dist: aicsimageprocessing (>=0.7.4)
Requires-Dist: matplotlib (>=3.2.0)
Requires-Dist: numpy (>=1.18.2)
Requires-Dist: pandas (>=1.0.3)
Provides-Extra: aics
Requires-Dist: lkaccess (>=1.4.25) ; extra == 'aics'
Provides-Extra: all
Requires-Dist: aics-dask-utils (>=0.2.0) ; extra == 'all'
Requires-Dist: bokeh (>=2.1.0) ; extra == 'all'
Requires-Dist: dask[bag] (>=2.19.0) ; extra == 'all'
Requires-Dist: dask-jobqueue (>=0.7.0) ; extra == 'all'
Requires-Dist: datastep (>=0.1.8) ; extra == 'all'
Requires-Dist: distributed (>=2.19.0) ; extra == 'all'
Requires-Dist: fire ; extra == 'all'
Requires-Dist: psutil ; extra == 'all'
Requires-Dist: aicsfeature (>=0.2.1) ; extra == 'all'
Requires-Dist: aicsimageio (>=3.2.3) ; extra == 'all'
Requires-Dist: aicsimageprocessing (>=0.7.4) ; extra == 'all'
Requires-Dist: matplotlib (>=3.2.0) ; extra == 'all'
Requires-Dist: numpy (>=1.18.2) ; extra == 'all'
Requires-Dist: pandas (>=1.0.3) ; extra == 'all'
Requires-Dist: pytest-runner (>=5.2) ; extra == 'all'
Requires-Dist: black (>=19.10b0) ; extra == 'all'
Requires-Dist: codecov (>=2.1.4) ; extra == 'all'
Requires-Dist: flake8 (>=3.8.3) ; extra == 'all'
Requires-Dist: flake8-debugger (>=3.2.1) ; extra == 'all'
Requires-Dist: pytest (>=5.4.3) ; extra == 'all'
Requires-Dist: pytest-cov (>=2.9.0) ; extra == 'all'
Requires-Dist: pytest-raises (>=0.11) ; extra == 'all'
Requires-Dist: quilt3 (>=3.1.10) ; extra == 'all'
Requires-Dist: bumpversion (>=0.6.0) ; extra == 'all'
Requires-Dist: coverage (>=5.1) ; extra == 'all'
Requires-Dist: ipython (>=7.15.0) ; extra == 'all'
Requires-Dist: m2r (>=0.2.1) ; extra == 'all'
Requires-Dist: Sphinx (<3,>=2.0.0b1) ; extra == 'all'
Requires-Dist: sphinx-rtd-theme (>=0.4.3) ; extra == 'all'
Requires-Dist: tox (>=3.15.2) ; extra == 'all'
Requires-Dist: twine (>=3.1.1) ; extra == 'all'
Requires-Dist: wheel (>=0.34.2) ; extra == 'all'
Provides-Extra: dev
Requires-Dist: pytest-runner (>=5.2) ; extra == 'dev'
Requires-Dist: black (>=19.10b0) ; extra == 'dev'
Requires-Dist: codecov (>=2.1.4) ; extra == 'dev'
Requires-Dist: flake8 (>=3.8.3) ; extra == 'dev'
Requires-Dist: flake8-debugger (>=3.2.1) ; extra == 'dev'
Requires-Dist: pytest (>=5.4.3) ; extra == 'dev'
Requires-Dist: pytest-cov (>=2.9.0) ; extra == 'dev'
Requires-Dist: pytest-raises (>=0.11) ; extra == 'dev'
Requires-Dist: quilt3 (>=3.1.10) ; extra == 'dev'
Requires-Dist: bumpversion (>=0.6.0) ; extra == 'dev'
Requires-Dist: coverage (>=5.1) ; extra == 'dev'
Requires-Dist: ipython (>=7.15.0) ; extra == 'dev'
Requires-Dist: m2r (>=0.2.1) ; extra == 'dev'
Requires-Dist: Sphinx (<3,>=2.0.0b1) ; extra == 'dev'
Requires-Dist: sphinx-rtd-theme (>=0.4.3) ; extra == 'dev'
Requires-Dist: tox (>=3.15.2) ; extra == 'dev'
Requires-Dist: twine (>=3.1.1) ; extra == 'dev'
Requires-Dist: wheel (>=0.34.2) ; extra == 'dev'
Provides-Extra: setup
Requires-Dist: pytest-runner (>=5.2) ; extra == 'setup'
Provides-Extra: test
Requires-Dist: black (>=19.10b0) ; extra == 'test'
Requires-Dist: codecov (>=2.1.4) ; extra == 'test'
Requires-Dist: flake8 (>=3.8.3) ; extra == 'test'
Requires-Dist: flake8-debugger (>=3.2.1) ; extra == 'test'
Requires-Dist: pytest (>=5.4.3) ; extra == 'test'
Requires-Dist: pytest-cov (>=2.9.0) ; extra == 'test'
Requires-Dist: pytest-raises (>=0.11) ; extra == 'test'
Requires-Dist: quilt3 (>=3.1.10) ; extra == 'test'
